LICENSE
README.md
setup.py
epl.protobuf.v1.egg-info/PKG-INFO
epl.protobuf.v1.egg-info/SOURCES.txt
epl.protobuf.v1.egg-info/dependency_links.txt
epl.protobuf.v1.egg-info/not-zip-safe
epl.protobuf.v1.egg-info/requires.txt
epl.protobuf.v1.egg-info/top_level.txt
epl/protobuf/v1/geometry_pb2.py
epl/protobuf/v1/geometry_service_pb2_grpc.py
epl/protobuf/v1/query_pb2.py
epl/protobuf/v1/stac_pb2.py
epl/protobuf/v1/stac_service_pb2_grpc.py